[
    {
        "Id": 685376,
        "CaseId": 234438,
        "VerdictDt": "/Date(1599771600000)/",
        "CreatedDate": "/Date(1599816126580)/",
        "VerdictsDtString": "11/09/2020",
        "CaseNum": 6363,
        "CaseDesc": "\u05e2\u05e2\"\u05de 6363-20",
        "Pages": 1,
        "Path": "HebrewVerdicts\\20\\630\\063\\o01",
        "PathForWeb": "HebrewVerdicts/20/630/063/o01",
        "CaseName": "\u05de\u05d3\u05d9\u05e0\u05ea \u05d9\u05e9\u05e8\u05d0\u05dc \u05e0. \u05e2\u05d5\u05de\u05e8 \u05d6\u05d9\u05d3 \u05d0\u05e1\u05d7\u05d0\u05e7 \u05e9\u05d5\u05d0",
        "FileName": "20063630.O01",
        "DocName": "20063630.O01.docx",
        "Content": null,
        "Year": 2020,
        "TypeCode": 1,
        "Type": "\u05d4\u05d7\u05dc\u05d8\u05d4",
        "CaseDt": null,
        "MadorDesc": null,
        "SeqNum": 0,
        "Technical": true,
        "FolderPath": "HebrewVerdicts\\20\\630\\063\\o01",
        "PageVolume": null,
        "DescVolume": null,
        "CodeVolume": 0,
        "liked": false,
        "InyanId": 25,
        "QuoteYear": 0,
        "CodeQuote": null,
        "CodeTitle": null,
        "VerdictDesc": null,
        "DocNumber": null,
        "Month": null,
        "free_text": null
    },
    {
        "Id": 685375,
        "CaseId": 233959,
        "VerdictDt": "/Date(1599771600000)/",
        "CreatedDate": "/Date(1599816124743)/",
        "VerdictsDtString": "11/09/2020",
        "CaseNum": 5887,
        "CaseDesc": "\u05d1\u05e9\"\u05e4 5887-20",
        "Pages": 1,
        "Path": "HebrewVerdicts\\20\\870\\058\\o03",
        "PathForWeb": "HebrewVerdicts/20/870/058/o03",
        "CaseName": "\u05d3\u05d0\u05e8\u05df \u05d1\u05d5\u05d1\u05e8\u05d5\u05e3 \u05e0. \u05de\u05d3\u05d9\u05e0\u05ea \u05d9\u05e9\u05e8\u05d0\u05dc",
        "FileName": "20058870.O03",
        "DocName": "20058870.O03.docx",
        "Content": null,
        "Year": 2020,
        "TypeCode": 1,
        "Type": "\u05d4\u05d7\u05dc\u05d8\u05d4",
        "CaseDt": null,
        "MadorDesc": null,
        "SeqNum": 0,
        "Technical": true,
        "FolderPath": "HebrewVerdicts\\20\\870\\058\\o03",
        "PageVolume": null,
        "DescVolume": null,
        "CodeVolume": 0,
        "liked": false,
        "InyanId": 14,
        "QuoteYear": 0,
        "CodeQuote": null,
        "CodeTitle": null,
        "VerdictDesc": null,
        "DocNumber": null,
        "Month": null,
        "free_text": null
    },
    {
        "Id": 685374,
        "CaseId": 234341,
        "VerdictDt": "/Date(1599771600000)/",
        "CreatedDate": "/Date(1599815177570)/",
        "VerdictsDtString": "11/09/2020",
        "CaseNum": 6268,
        "CaseDesc": "\u05d1\u05e9\"\u05e4 6268-20",
        "Pages": 2,
        "Path": "HebrewVerdicts\\20\\680\\062\\f01",
        "PathForWeb": "HebrewVerdicts/20/680/062/f01",
        "CaseName": "\u05e2\u05de\u05d9\u05ea \u05e8\u05d5\u05df \u05e0. \u05de\u05d3\u05d9\u05e0\u05ea \u05d9\u05e9\u05e8\u05d0\u05dc",
        "FileName": "20062680.F01",
        "DocName": "20062680.F01.docx",
        "Content": null,
        "Year": 2020,
        "TypeCode": 1,
        "Type": "\u05d4\u05d7\u05dc\u05d8\u05d4",
        "CaseDt": null,
        "MadorDesc": null,
        "SeqNum": 0,
        "Technical": true,
        "FolderPath": "HebrewVerdicts\\20\\680\\062\\f01",
        "PageVolume": null,
        "DescVolume": null,
        "CodeVolume": 0,
        "liked": false,
        "InyanId": 14,
        "QuoteYear": 0,
        "CodeQuote": null,
        "CodeTitle": null,
        "VerdictDesc": null,
        "DocNumber": null,
        "Month": null,
        "free_text": null
    },
    {
        "Id": 685373,
        "CaseId": 234281,
        "VerdictDt": "/Date(1599771600000)/",
        "CreatedDate": "/Date(1599815175503)/",
        "VerdictsDtString": "11/09/2020",
        "CaseNum": 6209,
        "CaseDesc": "\u05d1\u05e9\"\u05d0 6209-20",
        "Pages": 1,
        "Path": "HebrewVerdicts\\20\\090\\062\\f01",
        "PathForWeb": "HebrewVerdicts/20/090/062/f01",
        "CaseName": "\u05d0\u05d9\u05d9 \u05d0\u05d9 \u05d2'\u05d9 \u05d9\u05e9\u05e8\u05d0\u05dc \u05d7\u05d1\u05e8\u05d4 \u05dc\u05d1\u05d9\u05d8\u05d5\u05d7 \u05d1\u05e2\"\u05de \u05e0. \u05d0\u05dc\u05d9 \u05d8\u05d5\u05dc\u05d3\u05e0\u05d5",
        "FileName": "20062090.F01",
        "DocName": "20062090.F01.docx",
        "Content": null,
        "Year": 2020,
        "TypeCode": 1,
        "Type": "\u05d4\u05d7\u05dc\u05d8\u05d4",
        "CaseDt": null,
        "MadorDesc": null,
        "SeqNum": 0,
        "Technical": true,
        "FolderPath": "HebrewVerdicts\\20\\090\\062\\f01",
        "PageVolume": null,
        "DescVolume": null,
        "CodeVolume": 0,
        "liked": false,
        "InyanId": 2,
        "QuoteYear": 0,
        "CodeQuote": null,
        "CodeTitle": null,
        "VerdictDesc": null,
        "DocNumber": null,
        "Month": null,
        "free_text": [
            "\u05d1\u05d1\u05d9\u05ea \u05d4\u05de\u05e9\u05e4\u05d8 \u05d4\u05e2\u05dc\u05d9\u05d5\u05df",
            "\u05d1\u05e9\"\u05d0\u00a0 6209/20",
            "\u05dc\u05e4\u05e0\u05d9:",
            "\u05db\u05d1\u05d5\u05d3 \u05d4\u05e9\u05d5\u05e4\u05d8 \u05d0' \u05e9\u05d8\u05d9\u05d9\u05df",
            "\u05d4\u05de\u05d1\u05e7\u05e9\u05d9\u05dd:",
            "1. \u05d0\u05dc\u05d9 \u05d8\u05d5\u05dc\u05d3\u05e0\u05d5",
            "2. \u05e9\u05d9\u05e8\u05d1\u05d9\u05d8 \u05d7\u05d1\u05e8\u05d4 \u05dc\u05d1\u05d9\u05d8\u05d5\u05d7 \u05d1\u05e2\"\u05de",
            "\u05e0\u00a0 \u05d2\u00a0 \u05d3",
            "\u05d4\u05de\u05e9\u05d9\u05d1\u05d9\u05dd:",
            "1. \u05d0\u05d9\u05d9 \u05d0\u05d9 \u05d2'\u05d9 \u05d9\u05e9\u05e8\u05d0\u05dc \u05d7\u05d1\u05e8\u05d4 \u05dc\u05d1\u05d9\u05d8\u05d5\u05d7 \u05d1\u05e2\"\u05de",
            "2. \u05e1\u05d1\u05d9\u05df \u05de\u05d6\u05e8\u05d7\u05d9",
            "\u05d1\u05e7\u05e9\u05d4 \u05dc\u05d4\u05e2\u05d1\u05e8\u05ea \u05de\u05e7\u05d5\u05dd \u05d3\u05d9\u05d5\u05df",
            "\u05d1\u05e9\u05dd \u05d4\u05de\u05d1\u05e7\u05e9\u05d9\u05dd:",
            "\u05e2\u05d5\"\u05d3 \u05de\u05e9\u05d4 \u05de\u05e6\u05dc\u05d9\u05d7",
            "\u05d4\u05d7\u05dc\u05d8\u05d4",
            "1.\u00a0\u00a0\u00a0\u00a0\u00a0\u00a0 \u05dc\u05e4\u05e0\u05d9\u05d9 \u05d1\u05e7\u05e9\u05d4 \u05de\u05d5\u05e1\u05db\u05de\u05ea \u05dc\u05e4\u05d9 \u05e1\u05e2\u05d9\u05e3 78 \u05dc\u05d7\u05d5\u05e7\r\n\u05d1\u05ea\u05d9 \u05d4\u05de\u05e9\u05e4\u05d8 [\u05e0\u05d5\u05e1\u05d7 \u05de\u05e9\u05d5\u05dc\u05d1], \u05d4\u05ea\u05e9\u05de\"\u05d3-1984, \u05dc\u05d4\u05e2\u05d1\u05e8\u05ea \u05d4\u05d3\u05d9\u05d5\u05df \u05d1\u05ea\u05d0\"\u05de 8389-10-19\r\n\u05de\u05d1\u05d9\u05ea \u05de\u05e9\u05e4\u05d8 \u05d4\u05e9\u05dc\u05d5\u05dd \u05e4\u05ea\u05d7 \u05ea\u05e7\u05d5\u05d4 \u05dc\u05d1\u05d9\u05ea \u05de\u05e9\u05e4\u05d8 \u05d4\u05e9\u05dc\u05d5\u05dd \u05d0\u05d9\u05dc\u05ea. \u05de\u05d3\u05d5\u05d1\u05e8 \u05d1\u05ea\u05d1\u05d9\u05e2\u05d4 \u05e9\u05d4\u05d2\u05d9\u05e9\u05d5 \u05d4\u05de\u05e9\u05d9\u05d1\u05d9\u05dd \u05e0\u05d2\u05d3\r\n\u05d4\u05de\u05d1\u05e7\u05e9\u05d9\u05dd \u05d1\u05d2\u05d9\u05df \u05ea\u05d0\u05d5\u05e0\u05ea \u05d3\u05e8\u05db\u05d9\u05dd \u05e9\u05d0\u05d9\u05e8\u05e2\u05d4 \u05d1\u05d9\u05d5\u05dd 16.4.2019 \u05d1\u05e2\u05d9\u05e8 \u05d0\u05d9\u05dc\u05ea.",
            "2.\u00a0\u00a0\u00a0\u00a0\u00a0\u00a0 \u05dc\u05e0\u05d5\u05db\u05d7 \u05d4\u05e1\u05db\u05de\u05ea \u05d4\u05e6\u05d3\u05d3\u05d9\u05dd, \u05d5\u05d1\u05e9\u05d9\u05dd \u05dc\u05d1 \u05dc\u05e9\u05dc\u05d1 \u05d4\u05de\u05e7\u05d3\u05de\u05d9 \u05d1\u05d5 \u05de\u05e6\u05d5\u05d9\r\n\u05d4\u05d4\u05dc\u05d9\u05da, \u05d3\u05d9\u05df \u05d4\u05d1\u05e7\u05e9\u05d4 \u05dc\u05d4\u05ea\u05e7\u05d1\u05dc.",
            "3.\u00a0\u00a0\u00a0\u00a0\u00a0\u00a0 \u05d4\u05d3\u05d9\u05d5\u05df\r\n\u05d1\u05ea\u05d0\"\u05de 8389-10-19 (\u05e9\u05dc\u05d5\u05dd \u05e4\"\u05ea) \u05d9\u05d5\u05e2\u05d1\u05e8 \u05d0\u05e4\u05d5\u05d0 \u05dc\u05d1\u05d9\u05ea \u05de\u05e9\u05e4\u05d8 \u05d4\u05e9\u05dc\u05d5\u05dd \u05d0\u05d9\u05dc\u05ea.",
            "\u05e0\u05d9\u05ea\u05e0\u05d4\r\n\u05d4\u05d9\u05d5\u05dd, \u200f\u05db\"\u05d1 \u05d1\u05d0\u05dc\u05d5\u05dc \u05d4\u05ea\u05e9\"\u05e4 (\u200f11.9.2020).",
            "\u05e9 \u05d5 \u05e4 \u05d8",
            "_________________________",
            "20062090_F01.docx\u00a0\u00a0 \u05d4\u05e9",
            "\u05de\u05e8\u05db\u05d6 \u05de\u05d9\u05d3\u05e2, \u05d8\u05dc' 077-2703333, 3852* ;\r\n\u05d0\u05ea\u05e8 \u05d0\u05d9\u05e0\u05d8\u05e8\u05e0\u05d8,\u00a0 http://supreme.court.gov.il"
        ]
    },
    {
        "Id": 685372,
        "CaseId": 233951,
        "VerdictDt": "/Date(1599771600000)/",
        "CreatedDate": "/Date(1599815173473)/",
        "VerdictsDtString": "11/09/2020",
        "CaseNum": 5879,
        "CaseDesc": "\u05d1\u05e9\"\u05e4 5879-20",
        "Pages": 1,
        "Path": "HebrewVerdicts\\20\\790\\058\\f02",
        "PathForWeb": "HebrewVerdicts/20/790/058/f02",
        "CaseName": "\u05e8\u05e4\u05d0\u05dc \u05d0\u05dc\u05db\u05e1\u05e0\u05d3\u05e8 \u05d1\u05d9\u05e8\u05d5 \u05e0. \u05de\u05d3\u05d9\u05e0\u05ea \u05d9\u05e9\u05e8\u05d0\u05dc",
        "FileName": "20058790.F02",
        "DocName": "20058790.F02.docx",
        "Content": null,
        "Year": 2020,
        "TypeCode": 1,
        "Type": "\u05d4\u05d7\u05dc\u05d8\u05d4",
        "CaseDt": null,
        "MadorDesc": null,
        "SeqNum": 0,
        "Technical": true,
        "FolderPath": "HebrewVerdicts\\20\\790\\058\\f02",
        "PageVolume": null,
        "DescVolume": null,
        "CodeVolume": 0,
        "liked": false,
        "InyanId": 14,
        "QuoteYear": 0,
        "CodeQuote": null,
        "CodeTitle": null,
        "VerdictDesc": null,
        "DocNumber": null,
        "Month": null,
        "free_text": null
    },
    {
        "Id": 685371,
        "CaseId": 234405,
        "VerdictDt": "/Date(1599771600000)/",
        "CreatedDate": "/Date(1599806192463)/",
        "VerdictsDtString": "11/09/2020",
        "CaseNum": 6332,
        "CaseDesc": "\u05d1\u05e9\"\u05e4 6332-20",
        "Pages": 1,
        "Path": "HebrewVerdicts\\20\\320\\063\\f01",
        "PathForWeb": "HebrewVerdicts/20/320/063/f01",
        "CaseName": "\u05d0\u05d1\u05d5 \u05e0\u05d0\u05d1 \u05de\u05d5\u05e6\u05e2\u05d1 \u05e0. \u05de\u05d3\u05d9\u05e0\u05ea \u05d9\u05e9\u05e8\u05d0\u05dc",
        "FileName": "20063320.F01",
        "DocName": "20063320.F01.docx",
        "Content": null,
        "Year": 2020,
        "TypeCode": 1,
        "Type": "\u05d4\u05d7\u05dc\u05d8\u05d4",
        "CaseDt": null,
        "MadorDesc": null,
        "SeqNum": 0,
        "Technical": true,
        "FolderPath": "HebrewVerdicts\\20\\320\\063\\f01",
        "PageVolume": null,
        "DescVolume": null,
        "CodeVolume": 0,
        "liked": false,
        "InyanId": 14,
        "QuoteYear": 0,
        "CodeQuote": null,
        "CodeTitle": null,
        "VerdictDesc": null,
        "DocNumber": null,
        "Month": null,
        "free_text": null
    },
    {
        "Id": 685370,
        "CaseId": 234362,
        "VerdictDt": "/Date(1599771600000)/",
        "CreatedDate": "/Date(1599806190597)/",
        "VerdictsDtString": "11/09/2020",
        "CaseNum": 6289,
        "CaseDesc": "\u05d1\u05e9\"\u05d0 6289-20",
        "Pages": 2,
        "Path": "HebrewVerdicts\\20\\890\\062\\f01",
        "PathForWeb": "HebrewVerdicts/20/890/062/f01",
        "CaseName": "\u05e2\u05d1\u05d3\u05d0\u05dc\u05dc\u05d4 \u05d1\u05d3\u05e8\u05d0\u05df \u05e0. \u05e0\u05d0\u05d9\u05e3 \u05e1\u05e4\u05d9",
        "FileName": "20062890.F01",
        "DocName": "20062890.F01.docx",
        "Content": null,
        "Year": 2020,
        "TypeCode": 1,
        "Type": "\u05d4\u05d7\u05dc\u05d8\u05d4",
        "CaseDt": null,
        "MadorDesc": null,
        "SeqNum": 0,
        "Technical": true,
        "FolderPath": "HebrewVerdicts\\20\\890\\062\\f01",
        "PageVolume": null,
        "DescVolume": null,
        "CodeVolume": 0,
        "liked": false,
        "InyanId": 2,
        "QuoteYear": 0,
        "CodeQuote": null,
        "CodeTitle": null,
        "VerdictDesc": null,
        "DocNumber": null,
        "Month": null,
        "free_text": null
    },
    {
        "Id": 685369,
        "CaseId": 234332,
        "VerdictDt": "/Date(1599771600000)/",
        "CreatedDate": "/Date(1599806188687)/",
        "VerdictsDtString": "11/09/2020",
        "CaseNum": 6259,
        "CaseDesc": "\u05d1\u05e9\"\u05d0 6259-20",
        "Pages": 1,
        "Path": "HebrewVerdicts\\20\\590\\062\\f01",
        "PathForWeb": "HebrewVerdicts/20/590/062/f01",
        "CaseName": "\u05d4\u05e8\u05d0\u05dc \u05d7\u05d1\u05e8\u05d4 \u05dc\u05d1\u05d9\u05d8\u05d5\u05d7 \u05d1\u05e2\"\u05de \u05e0. \u05d9\u05e8\u05d3\u05df \u05d4\u05e1\u05e2\u05d5\u05ea \u05d1\u05e2\"\u05de",
        "FileName": "20062590.F01",
        "DocName": "20062590.F01.docx",
        "Content": null,
        "Year": 2020,
        "TypeCode": 1,
        "Type": "\u05d4\u05d7\u05dc\u05d8\u05d4",
        "CaseDt": null,
        "MadorDesc": null,
        "SeqNum": 0,
        "Technical": true,
        "FolderPath": "HebrewVerdicts\\20\\590\\062\\f01",
        "PageVolume": null,
        "DescVolume": null,
        "CodeVolume": 0,
        "liked": false,
        "InyanId": 2,
        "QuoteYear": 0,
        "CodeQuote": null,
        "CodeTitle": null,
        "VerdictDesc": null,
        "DocNumber": null,
        "Month": null,
        "free_text": null
    },
    {
        "Id": 685368,
        "CaseId": 234301,
        "VerdictDt": "/Date(1599771600000)/",
        "CreatedDate": "/Date(1599806184437)/",
        "VerdictsDtString": "11/09/2020",
        "CaseNum": 6228,
        "CaseDesc": "\u05d1\u05e9\"\u05e4 6228-20",
        "Pages": 1,
        "Path": "HebrewVerdicts\\20\\280\\062\\f01",
        "PathForWeb": "HebrewVerdicts/20/280/062/f01",
        "CaseName": "\u05d1\u05e0\u05de\u05d5 \u05d0\u05d1\u05e8\u05d4\u05dd \u05e0. \u05de\u05d3\u05d9\u05e0\u05ea \u05d9\u05e9\u05e8\u05d0\u05dc",
        "FileName": "20062280.F01",
        "DocName": "20062280.F01.docx",
        "Content": null,
        "Year": 2020,
        "TypeCode": 1,
        "Type": "\u05d4\u05d7\u05dc\u05d8\u05d4",
        "CaseDt": null,
        "MadorDesc": null,
        "SeqNum": 0,
        "Technical": true,
        "FolderPath": "HebrewVerdicts\\20\\280\\062\\f01",
        "PageVolume": null,
        "DescVolume": null,
        "CodeVolume": 0,
        "liked": false,
        "InyanId": 14,
        "QuoteYear": 0,
        "CodeQuote": null,
        "CodeTitle": null,
        "VerdictDesc": null,
        "DocNumber": null,
        "Month": null,
        "free_text": [
            "\u05d1\u05d1\u05d9\u05ea \u05d4\u05de\u05e9\u05e4\u05d8 \u05d4\u05e2\u05dc\u05d9\u05d5\u05df",
            "\u05d1\u05e9\"\u05e4\u00a0 6228/20",
            "\u05dc\u05e4\u05e0\u05d9:",
            "\u05db\u05d1\u05d5\u05d3 \u05d4\u05e9\u05d5\u05e4\u05d8 \u05d0' \u05e9\u05d8\u05d9\u05d9\u05df",
            "\u05d4\u05de\u05d1\u05e7\u05e9:",
            "\u05d1\u05e0\u05de\u05d5 \u05d0\u05d1\u05e8\u05d4\u05dd",
            "\u05e0\u00a0 \u05d2\u00a0 \u05d3",
            "\u05d4\u05de\u05e9\u05d9\u05d1\u05d4:",
            "\u05de\u05d3\u05d9\u05e0\u05ea \u05d9\u05e9\u05e8\u05d0\u05dc",
            "\u05d1\u05e7\u05e9\u05d4 \u05dc\u05d4\u05e2\u05d1\u05e8\u05ea \u05de\u05e7\u05d5\u05dd \u05d3\u05d9\u05d5\u05df",
            "\u05d1\u05e9\u05dd \u05d4\u05de\u05d1\u05e7\u05e9:",
            "\u05d1\u05e2\u05e6\u05de\u05d5",
            "\u05d4\u05d7\u05dc\u05d8\u05d4",
            "1.\u00a0\u00a0\u00a0\u00a0\u00a0\u00a0 \u05dc\u05e4\u05e0\u05d9\u05d9 \u05d1\u05e7\u05e9\u05d4 \u05dc\u05e4\u05d9 \u05e1\u05e2\u05d9\u05e3 78 \u05dc\u05d7\u05d5\u05e7 \u05d1\u05ea\u05d9 \u05d4\u05de\u05e9\u05e4\u05d8 [\u05e0\u05d5\u05e1\u05d7\r\n\u05de\u05e9\u05d5\u05dc\u05d1], \u05d4\u05ea\u05e9\u05de\"\u05d3-1984,\u00a0 \u05dc\u05d4\u05e2\u05d1\u05e8\u05ea \u05de\u05e7\u05d5\u05dd \u05d4\u05d3\u05d9\u05d5\u05df\r\n\u05d1\u05ea\u05ea\u05f4\u05e2 6987-04-20 \u05de\u05d1\u05d9\u05ea \u05de\u05e9\u05e4\u05d8 \u05d4\u05e9\u05dc\u05d5\u05dd \u05dc\u05ea\u05e2\u05d1\u05d5\u05e8\u05d4 \u05d7\u05d9\u05e4\u05d4 \u05dc\u05d1\u05d9\u05ea \u05de\u05e9\u05e4\u05d8 \u05d4\u05e9\u05dc\u05d5\u05dd \u05dc\u05ea\u05e2\u05d1\u05d5\u05e8\u05d4 \u05d9\u05e8\u05d5\u05e9\u05dc\u05d9\u05dd.",
            "2.\u00a0\u00a0\u00a0\u00a0\u00a0\u00a0 \u05db\u05e2\u05d5\u05dc\u05d4 \u05de\u05df \u05d4\u05d1\u05e7\u05e9\u05d4, \u05d4\u05ea\u05d9\u05e7 \u05e0\u05e7\u05d1\u05e2 \u05dc\u05d3\u05d9\u05d5\u05df \u05d1\u05d9\u05d5\u05dd 29.9.2020 \u05d5\u05d8\u05e8\u05dd\r\n\u05e7\u05d5\u05d9\u05d9\u05de\u05d4 \u05d1\u05d5 \u05d4\u05e7\u05e8\u05d0\u05d4. \u05d4\u05de\u05d1\u05e7\u05e9 \u05de\u05ea\u05d2\u05d5\u05e8\u05e8 \u05d1\u05de\u05e8\u05d7\u05e7 \u05d2\u05d9\u05d0\u05d5\u05d2\u05e8\u05e4\u05d9 \u05e8\u05d1 \u05d9\u05d7\u05e1\u05d9\u05ea \u05de\u05d1\u05d9\u05ea \u05de\u05e9\u05e4\u05d8 \u05d4\u05e9\u05dc\u05d5\u05dd \u05dc\u05ea\u05e2\u05d1\u05d5\u05e8\u05d4 \u05d7\u05d9\u05e4\u05d4\r\n\u05d5\u05de\u05e6\u05d4\u05d9\u05e8 \u05db\u05d9 \u05d4\u05d5\u05d0 \u05de\u05d5\u05d3\u05d4 \u05d1\u05de\u05d9\u05d5\u05d7\u05e1 \u05dc\u05d5 \u05d1\u05db\u05ea\u05d1 \u05d4\u05d0\u05d9\u05e9\u05d5\u05dd.",
            "3.\u00a0\u00a0\u00a0\u00a0\u00a0\u00a0 \u05dc\u05e0\u05d5\u05db\u05d7 \u05d4\u05d0\u05de\u05d5\u05e8, \u05d3\u05d9\u05df \u05d4\u05d1\u05e7\u05e9\u05d4 \u05dc\u05d4\u05ea\u05e7\u05d1\u05dc.",
            "4.\u00a0\u00a0\u00a0\u00a0\u00a0\u00a0 \u05d4\u05d3\u05d9\u05d5\u05df\r\n\u05d1\u05ea\u05d9\u05e7 \u05d9\u05d5\u05e2\u05d1\u05e8 \u05d0\u05e4\u05d5\u05d0 \u05dc\u05d1\u05d9\u05ea \u05de\u05e9\u05e4\u05d8 \u05d4\u05e9\u05dc\u05d5\u05dd \u05dc\u05ea\u05e2\u05d1\u05d5\u05e8\u05d4 \u05d9\u05e8\u05d5\u05e9\u05dc\u05d9\u05dd.",
            "\u05e0\u05d9\u05ea\u05e0\u05d4\r\n\u05d4\u05d9\u05d5\u05dd, \u200f\u05db\"\u05d1 \u05d1\u05d0\u05dc\u05d5\u05dc \u05d4\u05ea\u05e9\"\u05e4 (\u200f11.9.2020).",
            "\u05e9 \u05d5 \u05e4 \u05d8",
            "_________________________",
            "20062280_F01.docx\u00a0\u00a0 \u05e2\u05d1",
            "\u05de\u05e8\u05db\u05d6 \u05de\u05d9\u05d3\u05e2, \u05d8\u05dc' 077-2703333, 3852* ;\r\n\u05d0\u05ea\u05e8 \u05d0\u05d9\u05e0\u05d8\u05e8\u05e0\u05d8,\u00a0 http://supreme.court.gov.il"
        ]
    },
    {
        "Id": 685367,
        "CaseId": 234110,
        "VerdictDt": "/Date(1599771600000)/",
        "CreatedDate": "/Date(1599806182543)/",
        "VerdictsDtString": "11/09/2020",
        "CaseNum": 6039,
        "CaseDesc": "\u05d1\u05e9\"\u05d0 6039-20",
        "Pages": 2,
        "Path": "HebrewVerdicts\\20\\390\\060\\f02",
        "PathForWeb": "HebrewVerdicts/20/390/060/f02",
        "CaseName": "\u05e1\u05e7\u05d5\u05e8\u05d9\u05d8\u05e1 \u05e1\u05d5\u05db\u05e0\u05d5\u05ea \u05d1\u05d9\u05d8\u05d5\u05d7 \u05d1\u05e2\"\u05de \u05e0. \u05e9\u05d5\u05de\u05e8\u05d4 \u05d7\u05d1\u05e8\u05d4 \u05dc\u05d1\u05d9\u05d8\u05d5\u05d7 \u05d1\u05e2\"\u05de",
        "FileName": "20060390.F02",
        "DocName": "20060390.F02.docx",
        "Content": null,
        "Year": 2020,
        "TypeCode": 1,
        "Type": "\u05d4\u05d7\u05dc\u05d8\u05d4",
        "CaseDt": null,
        "MadorDesc": null,
        "SeqNum": 0,
        "Technical": true,
        "FolderPath": "HebrewVerdicts\\20\\390\\060\\f02",
        "PageVolume": null,
        "DescVolume": null,
        "CodeVolume": 0,
        "liked": false,
        "InyanId": 2,
        "QuoteYear": 0,
        "CodeQuote": null,
        "CodeTitle": null,
        "VerdictDesc": null,
        "DocNumber": null,
        "Month": null,
        "free_text": [
            "\u05d1\u05d1\u05d9\u05ea \u05d4\u05de\u05e9\u05e4\u05d8 \u05d4\u05e2\u05dc\u05d9\u05d5\u05df",
            "\u05d1\u05e9\"\u05d0\u00a0 6039/20",
            "\u05dc\u05e4\u05e0\u05d9:",
            "\u05db\u05d1\u05d5\u05d3 \u05d4\u05e9\u05d5\u05e4\u05d8 \u05d0' \u05e9\u05d8\u05d9\u05d9\u05df",
            "\u05d4\u05de\u05d1\u05e7\u05e9\u05ea:",
            "\u05e1\u05e7\u05d5\u05e8\u05d9\u05d8\u05e1 \u05e1\u05d5\u05db\u05e0\u05d5\u05ea \u05d1\u05d9\u05d8\u05d5\u05d7 \u05d1\u05e2\"\u05de",
            "\u05e0\u00a0 \u05d2\u00a0 \u05d3",
            "\u05d4\u05de\u05e9\u05d9\u05d1\u05d4:",
            "\u05e9\u05d5\u05de\u05e8\u05d4 \u05d7\u05d1\u05e8\u05d4 \u05dc\u05d1\u05d9\u05d8\u05d5\u05d7 \u05d1\u05e2\"\u05de",
            "\u05d1\u05e7\u05e9\u05d4 \u05dc\u05d4\u05e2\u05d1\u05e8\u05ea \u05de\u05e7\u05d5\u05dd \u05d3\u05d9\u05d5\u05df",
            "\u05d1\u05e9\u05dd \u05d4\u05de\u05d1\u05e7\u05e9\u05ea:",
            "\u05e2\u05d5\"\u05d3 \u05de\u05d9\u05d9\u05e7\u05dc \u05e9\u05d5\u05e8\u05e7\u05d9\u05df",
            "\u05d4\u05d7\u05dc\u05d8\u05d4",
            "1.\u00a0\u00a0\u00a0\u00a0\u00a0\u00a0 \u05dc\u05e4\u05e0\u05d9\u05d9 \u05d1\u05e7\u05e9\u05d4\r\n\u05dc\u05e4\u05d9 \u05e1\u05e2\u05d9\u05e3 78 \u05dc\u05d7\u05d5\u05e7 \u05d1\u05ea\u05d9 \u05d4\u05de\u05e9\u05e4\u05d8 [\u05e0\u05d5\u05e1\u05d7 \u05de\u05e9\u05d5\u05dc\u05d1], \u05d4\u05ea\u05e9\u05de\"\u05d3-1984 (\u05dc\u05d4\u05dc\u05df: \u05d7\u05d5\u05e7 \u05d1\u05ea\u05d9 \u05d4\u05de\u05e9\u05e4\u05d8), \u05dc\u05d4\u05e2\u05d1\u05e8\u05ea \u05d4\u05d3\u05d9\u05d5\u05df \u05d1\u05ea\u05d0\"\u05de 2683-04-20 \u05de\u05d1\u05d9\u05ea \u05de\u05e9\u05e4\u05d8 \u05d4\u05e9\u05dc\u05d5\u05dd\r\n\u05e4\u05ea\u05d7 \u05ea\u05e7\u05d5\u05d4 \u05dc\u05d1\u05d9\u05ea \u05de\u05e9\u05e4\u05d8 \u05d4\u05e9\u05dc\u05d5\u05dd \u05e7\u05e8\u05d9\u05d5\u05ea. \u05de\u05d3\u05d5\u05d1\u05e8 \u05d1\u05ea\u05d1\u05d9\u05e2\u05d4 \u05e9\u05e2\u05e0\u05d9\u05d9\u05e0\u05d4 \u05ea\u05d0\u05d5\u05e0\u05ea \u05d3\u05e8\u05db\u05d9\u05dd \u05e9\u05d0\u05d9\u05e8\u05e2\u05d4 \u05d1\u05d9\u05d5\u05dd\r\n20.11.2018 \u05d1\u05d3\u05dc\u05d9\u05ea \u05d0\u05dc-\u05db\u05e8\u05de\u05dc.",
            "2. \u00a0\u00a0\u00a0\u00a0\u00a0 \u05db\u05de\u05d5\u05e1\u05d1\u05e8\r\n\u05d1\u05d1\u05e9\u05f4\u05d0 5948/18 \u05de\u05d3\u05d9\u05e0\u05ea \u05d9\u05e9\u05e8\u05d0\u05dc \u05e0\u05f3\r\n\u05e4\u05dc\u05d5\u05e0\u05d9\u05ea (6.9.2018), \u05d4\u05ea\u05d5\u05d1\u05e2\r\n\u05d6\u05db\u05d0\u05d9 \u05dc\u05db\u05da \u05e9\u05ea\u05d1\u05d9\u05e2\u05ea\u05d5 \u05ea\u05ea\u05d1\u05e8\u05e8 \u05d1\u05d1\u05d9\u05ea \u05de\u05e9\u05e4\u05d8 \u05de\u05d5\u05e1\u05de\u05da \u05e9\u05d1\u05d5 \u05d4\u05d5\u05d0 \u05d1\u05d7\u05e8 \u05dc\u05d4\u05d2\u05d9\u05e9\u05d4. \u05d6\u05db\u05d5\u05ea \u05d6\u05d5 \u05de\u05d4\u05d5\u05d5\u05d4 \u05e0\u05e7\u05d5\u05d3\u05ea\r\n\u05de\u05d5\u05e6\u05d0 \u05dc\u05d3\u05d9\u05d5\u05df \u05d5\u05d4\u05db\u05e8\u05e2\u05d4 \u05d1\u05d1\u05e7\u05e9\u05d5\u05ea \u05d4\u05e2\u05d1\u05e8\u05d4 \u05d0\u05e9\u05e8 \u05de\u05d5\u05d2\u05e9\u05d5\u05ea \u05e2\u05dc \u05d9\u05d3\u05d9 \u05e0\u05ea\u05d1\u05e2\u05d9\u05dd \u05d5\u05e6\u05d3\u05d3\u05d9\u05dd \u05e9\u05dc\u05d9\u05e9\u05d9\u05d9\u05dd \u05d1\u05d4\u05d9\u05e9\u05e2\u05df\r\n\u05e2\u05dc \u05e1\u05e2\u05d9\u05e3 78 \u05dc\u05d7\u05d5\u05e7 \u05d1\u05ea\u05d9 \u05d4\u05de\u05e9\u05e4\u05d8. \u05e0\u05e7\u05d5\u05d3\u05ea \u05de\u05d5\u05e6\u05d0 \u05d6\u05d5 \u05d0\u05d9\u05e0\u05e0\u05d4 \u05ea\u05de\u05d9\u05d3 \u05d6\u05d4\u05d4 \u05dc\u05e0\u05e7\u05d5\u05d3\u05ea \u05d4\u05e1\u05d9\u05d5\u05dd, \u05e9\u05db\u05df \u05e7\u05d5\u05e8\u05d4\r\n\u05dc\u05d0 \u05d0\u05d7\u05ea \u05e9\u05d4\u05e0\u05ea\u05d1\u05e2 (\u05d0\u05d5 \u05e6\u05d3 \u05e9\u05dc\u05d9\u05e9\u05d9) \u05de\u05e9\u05db\u05e0\u05e2\u05e0\u05d5 \u05d1\u05e0\u05d7\u05d9\u05e6\u05d5\u05ea \u05d4\u05d4\u05e2\u05d1\u05e8\u05d4. \u05de\u05d1\u05e7\u05e9 \u05d4\u05d4\u05e2\u05d1\u05e8\u05d4 \u05de\u05e8\u05d9\u05dd \u05d0\u05ea \u05e0\u05d8\u05dc\r\n\u05d4\u05e9\u05db\u05e0\u05d5\u05e2 \u05d4\u05de\u05d5\u05d8\u05dc \u05e2\u05dc\u05d9\u05d5 \u05db\u05d0\u05e9\u05e8 \u05d4\u05d5\u05d0 \u05de\u05e8\u05d0\u05d4 \u05db\u05d9 \u05d4\u05e7\u05e9\u05e8 \u05e9\u05d1\u05d9\u05df \u05d1\u05d9\u05ea \u05d4\u05de\u05e9\u05e4\u05d8 \u05e9\u05d1\u05d5 \u05d1\u05d7\u05e8 \u05d4\u05ea\u05d5\u05d1\u05e2 \u05dc\u05d4\u05d2\u05d9\u05e9 \u05d0\u05ea\r\n\u05ea\u05d1\u05d9\u05e2\u05ea\u05d5 \u05dc\u05d1\u05d9\u05df \u05de\u05e7\u05d5\u05dd \u05d4\u05d0\u05d9\u05e8\u05d5\u05e2 \u05d4\u05e2\u05d5\u05de\u05d3 \u05dc\u05d3\u05d9\u05d5\u05df \u05d5\u05de\u05e7\u05d5\u05dd \u05de\u05d5\u05e9\u05d1\u05dd \u05e9\u05dc \u05d1\u05e2\u05dc\u05d9 \u05d4\u05d3\u05d9\u05df \u05d5\u05e2\u05d3\u05d9\u05d4\u05dd \u05d4\u05d9\u05e0\u05d5 \u05e8\u05d5\u05e4\u05e3\r\n\u05e2\u05d3 \u05db\u05d3\u05d9 \u05de\u05dc\u05d0\u05db\u05d5\u05ea\u05d9.",
            "3. \u00a0\u00a0\u00a0\u00a0\u00a0 \u05d4\u05de\u05d1\u05e7\u05e9\u05ea\r\n\u05d3\u05e0\u05df \u05d4\u05e8\u05d9\u05de\u05d4 \u05e0\u05d8\u05dc \u05d6\u05d4 \u05d1\u05d4\u05e6\u05dc\u05d7\u05d4. \u05de\u05d4\u05d1\u05e7\u05e9\u05d4 \u05e2\u05d5\u05dc\u05d4 \u05db\u05d9 \u05d4\u05ea\u05d0\u05d5\u05e0\u05d4 \u05d0\u05d9\u05e8\u05e2\u05d4 \u05d1\u05d3\u05dc\u05d9\u05ea \u05d0\u05dc \u05db\u05e8\u05de\u05dc, \u05d5\u05d4\u05e2\u05d3\u05d9\u05dd \u05d4\u05e4\u05d5\u05d8\u05e0\u05e6\u05d9\u05d0\u05dc\u05d9\u05d9\u05dd \u05de\u05ea\u05d2\u05d5\u05e8\u05e8\u05d9\u05dd\r\n\u05d1\u05e2\u05d9\u05e8 \u05d7\u05d9\u05e4\u05d4. \u05d1\u05e0\u05e1\u05d9\u05d1\u05d5\u05ea \u05d0\u05dc\u05d4, \u05de\u05d0\u05d6\u05df\r\n\u05d4\u05e0\u05d5\u05d7\u05d5\u05ea \u05e0\u05d5\u05d8\u05d4 \u05d1\u05d1\u05d9\u05e8\u05d5\u05e8 \u05dc\u05d8\u05d5\u05d1\u05ea \u05d4\u05e2\u05d1\u05e8\u05ea \u05d4\u05d3\u05d9\u05d5\u05df \u05dc\u05d1\u05d9\u05ea \u05de\u05e9\u05e4\u05d8 \u05d4\u05e9\u05dc\u05d5\u05dd \u05e7\u05e8\u05d9\u05d5\u05ea.",
            "4.\u00a0\u00a0\u00a0\u00a0\u00a0\u00a0 \u05d0\u05e9\u05e8\r\n\u05e2\u05dc \u05db\u05df, \u05d0\u05e0\u05d9 \u05de\u05e7\u05d1\u05dc \u05d0\u05ea \u05d4\u05d1\u05e7\u05e9\u05d4 \u05d5\u05de\u05e2\u05d1\u05d9\u05e8 \u05d0\u05ea \u05d4\u05d3\u05d9\u05d5\u05df \u05d1\u05ea\u05d0\"\u05de 2683-04-20 (\u05e9\u05dc\u05d5\u05dd \u05e4\"\u05ea)\r\n\u05dc\u05d1\u05d9\u05ea \u05de\u05e9\u05e4\u05d8 \u05d4\u05e9\u05dc\u05d5\u05dd \u05e7\u05e8\u05d9\u05d5\u05ea.",
            "\u05e0\u05d9\u05ea\u05e0\u05d4\r\n\u05d4\u05d9\u05d5\u05dd, \u200f\u05db\"\u05d1 \u05d1\u05d0\u05dc\u05d5\u05dc \u05d4\u05ea\u05e9\"\u05e4 (\u200f11.9.2020).",
            "\u05e9 \u05d5 \u05e4 \u05d8",
            "_________________________",
            "20060390_F02.docx\u00a0\u00a0 \u05e2\u05d1",
            "\u05de\u05e8\u05db\u05d6 \u05de\u05d9\u05d3\u05e2, \u05d8\u05dc' 077-2703333, 3852* ;\r\n\u05d0\u05ea\u05e8 \u05d0\u05d9\u05e0\u05d8\u05e8\u05e0\u05d8,\u00a0 http://supreme.court.gov.il"
        ]
    },
    {
        "Id": 685366,
        "CaseId": 233993,
        "VerdictDt": "/Date(1599771600000)/",
        "CreatedDate": "/Date(1599806180043)/",
        "VerdictsDtString": "11/09/2020",
        "CaseNum": 5921,
        "CaseDesc": "\u05d1\u05e9\"\u05d0 5921-20",
        "Pages": 2,
        "Path": "HebrewVerdicts\\20\\210\\059\\f02",
        "PathForWeb": "HebrewVerdicts/20/210/059/f02",
        "CaseName": "\u05d7\u05d5\u05e1\u05d9\u05d9\u05df \u05d2'\u05d0\u05d1\u05e8\u05d9\u05df \u05e0. \u05e7.\u05e9. \u05d7\u05ea\u05de\u05d9\u05dd \u05d1\u05d9\u05e0\u05dc\u05d0\u05d5\u05de\u05d9\u05d9\u05dd \u05e1\u05d5\u05db\u05e0\u05d5\u05ea \u05dc\u05d1\u05d9\u05d8\u05d5\u05d7 \u05db\u05dc\u05dc\u05d9 (",
        "FileName": "20059210.F02",
        "DocName": "20059210.F02.docx",
        "Content": null,
        "Year": 2020,
        "TypeCode": 1,
        "Type": "\u05d4\u05d7\u05dc\u05d8\u05d4",
        "CaseDt": null,
        "MadorDesc": null,
        "SeqNum": 0,
        "Technical": true,
        "FolderPath": "HebrewVerdicts\\20\\210\\059\\f02",
        "PageVolume": null,
        "DescVolume": null,
        "CodeVolume": 0,
        "liked": false,
        "InyanId": 2,
        "QuoteYear": 0,
        "CodeQuote": null,
        "CodeTitle": null,
        "VerdictDesc": null,
        "DocNumber": null,
        "Month": null,
        "free_text": null
    }
]