[
    {
        "Id": 736830,
        "CaseId": 250723,
        "VerdictDt": "/Date(1656622800000)/",
        "CreatedDate": "/Date(1656919804513)/",
        "VerdictsDtString": "01/07/2022",
        "CaseNum": 4347,
        "CaseDesc": "\u05e2\u05de\"\u05de 4347-22",
        "Pages": 3,
        "Path": "HebrewVerdicts\\22\\470\\043\\05x",
        "PathForWeb": "HebrewVerdicts/22/470/043/05x",
        "CaseName": "\u05e4\u05dc\u05d5\u05e0\u05d9 \u05e0. \u05de\u05d3\u05d9\u05e0\u05ea \u05d9\u05e9\u05e8\u05d0\u05dc",
        "FileName": "22043470.05X",
        "DocName": "22043470.05X.docx",
        "Content": null,
        "Year": 2022,
        "TypeCode": 1,
        "Type": "\u05d4\u05d7\u05dc\u05d8\u05d4",
        "CaseDt": null,
        "MadorDesc": null,
        "SeqNum": 0,
        "Technical": false,
        "FolderPath": "HebrewVerdicts\\22\\470\\043\\05x",
        "PageVolume": null,
        "DescVolume": null,
        "CodeVolume": 0,
        "liked": false,
        "InyanId": 21,
        "QuoteYear": 0,
        "CodeQuote": null,
        "CodeTitle": null,
        "VerdictDesc": null,
        "DocNumber": null,
        "Month": null,
        "free_text": null
    },
    {
        "Id": 736663,
        "CaseId": 250738,
        "VerdictDt": "/Date(1656622800000)/",
        "CreatedDate": "/Date(1656668834367)/",
        "VerdictsDtString": "01/07/2022",
        "CaseNum": 4362,
        "CaseDesc": "\u05d1\u05e9\"\u05e4 4362-22",
        "Pages": 9,
        "Path": "HebrewVerdicts\\22\\620\\043\\x02",
        "PathForWeb": "HebrewVerdicts/22/620/043/x02",
        "CaseName": "\u05de\u05d3\u05d9\u05e0\u05ea \u05d9\u05e9\u05e8\u05d0\u05dc \u05e0. \u05e4\u05e8\u05d0\u05e1 \u05d8\u05d5\u05d8\u05d7",
        "FileName": "22043620.X02",
        "DocName": "22043620.X02.docx",
        "Content": null,
        "Year": 2022,
        "TypeCode": 1,
        "Type": "\u05d4\u05d7\u05dc\u05d8\u05d4",
        "CaseDt": null,
        "MadorDesc": null,
        "SeqNum": 0,
        "Technical": false,
        "FolderPath": "HebrewVerdicts\\22\\620\\043\\x02",
        "PageVolume": null,
        "DescVolume": null,
        "CodeVolume": 0,
        "liked": false,
        "InyanId": 14,
        "QuoteYear": 0,
        "CodeQuote": null,
        "CodeTitle": null,
        "VerdictDesc": null,
        "DocNumber": null,
        "Month": null,
        "free_text": null
    },
    {
        "Id": 736662,
        "CaseId": 250851,
        "VerdictDt": "/Date(1656622800000)/",
        "CreatedDate": "/Date(1656667886493)/",
        "VerdictsDtString": "01/07/2022",
        "CaseNum": 4475,
        "CaseDesc": "\u05d1\u05e9\"\u05e4 4475-22",
        "Pages": 1,
        "Path": "HebrewVerdicts\\22\\750\\044\\x01",
        "PathForWeb": "HebrewVerdicts/22/750/044/x01",
        "CaseName": "\u05de\u05d3\u05d9\u05e0\u05ea \u05d9\u05e9\u05e8\u05d0\u05dc \u05e0. \u05d7'\u05dc\u05d9\u05dc \u05d0\u05d2\u05d1\u05d0\u05e8\u05d9\u05d4",
        "FileName": "22044750.X01",
        "DocName": "22044750.X01.docx",
        "Content": null,
        "Year": 2022,
        "TypeCode": 1,
        "Type": "\u05d4\u05d7\u05dc\u05d8\u05d4",
        "CaseDt": null,
        "MadorDesc": null,
        "SeqNum": 0,
        "Technical": false,
        "FolderPath": "HebrewVerdicts\\22\\750\\044\\x01",
        "PageVolume": null,
        "DescVolume": null,
        "CodeVolume": 0,
        "liked": false,
        "InyanId": 14,
        "QuoteYear": 0,
        "CodeQuote": null,
        "CodeTitle": null,
        "VerdictDesc": null,
        "DocNumber": null,
        "Month": null,
        "free_text": null
    },
    {
        "Id": 736661,
        "CaseId": 250852,
        "VerdictDt": "/Date(1656622800000)/",
        "CreatedDate": "/Date(1656666939130)/",
        "VerdictsDtString": "01/07/2022",
        "CaseNum": 4476,
        "CaseDesc": "\u05d1\u05e9\"\u05e4 4476-22",
        "Pages": 1,
        "Path": "HebrewVerdicts\\22\\760\\044\\x01",
        "PathForWeb": "HebrewVerdicts/22/760/044/x01",
        "CaseName": "\u05de\u05d3\u05d9\u05e0\u05ea \u05d9\u05e9\u05e8\u05d0\u05dc \u05e0. \u05d1\u05e0\u05d9\u05de\u05d9\u05df \u05d6\u05d0\u05d1\u05d9",
        "FileName": "22044760.X01",
        "DocName": "22044760.X01.docx",
        "Content": null,
        "Year": 2022,
        "TypeCode": 1,
        "Type": "\u05d4\u05d7\u05dc\u05d8\u05d4",
        "CaseDt": null,
        "MadorDesc": null,
        "SeqNum": 0,
        "Technical": false,
        "FolderPath": "HebrewVerdicts\\22\\760\\044\\x01",
        "PageVolume": null,
        "DescVolume": null,
        "CodeVolume": 0,
        "liked": false,
        "InyanId": 14,
        "QuoteYear": 0,
        "CodeQuote": null,
        "CodeTitle": null,
        "VerdictDesc": null,
        "DocNumber": null,
        "Month": null,
        "free_text": null
    },
    {
        "Id": 736660,
        "CaseId": 250811,
        "VerdictDt": "/Date(1656622800000)/",
        "CreatedDate": "/Date(1656663342150)/",
        "VerdictsDtString": "01/07/2022",
        "CaseNum": 4436,
        "CaseDesc": "\u05d1\u05d2\"\u05e5 4436-22",
        "Pages": 1,
        "Path": "HebrewVerdicts\\22\\360\\044\\x01",
        "PathForWeb": "HebrewVerdicts/22/360/044/x01",
        "CaseName": "\u05d4\u05ea\u05d0\u05d7\u05d3\u05d5\u05ea \u05d4\u05ea\u05e2\u05e9\u05d9\u05d9\u05e0\u05d9\u05dd \u05d1\u05d9\u05e9\u05e8\u05d0\u05dc \u05e0. \u05d4\u05de\u05e9\u05e8\u05d3 \u05dc\u05d4\u05d2\u05e0\u05ea \u05d4\u05e1\u05d1\u05d9\u05d1\u05d4",
        "FileName": "22044360.X01",
        "DocName": "22044360.X01.docx",
        "Content": null,
        "Year": 2022,
        "TypeCode": 1,
        "Type": "\u05d4\u05d7\u05dc\u05d8\u05d4",
        "CaseDt": null,
        "MadorDesc": null,
        "SeqNum": 0,
        "Technical": true,
        "FolderPath": "HebrewVerdicts\\22\\360\\044\\x01",
        "PageVolume": null,
        "DescVolume": null,
        "CodeVolume": 0,
        "liked": false,
        "InyanId": 8,
        "QuoteYear": 0,
        "CodeQuote": null,
        "CodeTitle": null,
        "VerdictDesc": null,
        "DocNumber": null,
        "Month": null,
        "free_text": null
    },
    {
        "Id": 736653,
        "CaseId": 250844,
        "VerdictDt": "/Date(1656622800000)/",
        "CreatedDate": "/Date(1656659732803)/",
        "VerdictsDtString": "01/07/2022",
        "CaseNum": 4469,
        "CaseDesc": "\u05d1\u05d2\"\u05e5 4469-22",
        "Pages": 1,
        "Path": "HebrewVerdicts\\22\\690\\044\\x03",
        "PathForWeb": "HebrewVerdicts/22/690/044/x03",
        "CaseName": "\u05d0\u05e8\u05d2\u05d5\u05df \u05de\u05d2\u05d3\u05dc\u05d9 \u05d4\u05d3\u05d1\u05d5\u05e8\u05d9\u05dd \u05d1\u05d9\u05e9\u05e8\u05d0\u05dc \u05e0. \u05de\u05de\u05e9\u05dc\u05ea \u05d9\u05e9\u05e8\u05d0\u05dc",
        "FileName": "22044690.X03",
        "DocName": "22044690.X03.docx",
        "Content": null,
        "Year": 2022,
        "TypeCode": 1,
        "Type": "\u05d4\u05d7\u05dc\u05d8\u05d4",
        "CaseDt": null,
        "MadorDesc": null,
        "SeqNum": 0,
        "Technical": true,
        "FolderPath": "HebrewVerdicts\\22\\690\\044\\x03",
        "PageVolume": null,
        "DescVolume": null,
        "CodeVolume": 0,
        "liked": false,
        "InyanId": 8,
        "QuoteYear": 0,
        "CodeQuote": null,
        "CodeTitle": null,
        "VerdictDesc": null,
        "DocNumber": null,
        "Month": null,
        "free_text": null
    },
    {
        "Id": 736652,
        "CaseId": 250837,
        "VerdictDt": "/Date(1656622800000)/",
        "CreatedDate": "/Date(1656659730820)/",
        "VerdictsDtString": "01/07/2022",
        "CaseNum": 4462,
        "CaseDesc": "\u05d1\u05d2\"\u05e5 4462-22",
        "Pages": 1,
        "Path": "HebrewVerdicts\\22\\620\\044\\x01",
        "PathForWeb": "HebrewVerdicts/22/620/044/x01",
        "CaseName": "\u05e2\u05d5\"\u05d3 \u05d0\u05dc\u05db\u05e1\u05e0\u05d3\u05e8 \u05d2\u05de\u05d1\u05e8\u05d9\u05d0\u05df \u05e0. \u05de\u05e9\u05e8\u05d3 \u05d4\u05e4\u05e0\u05d9\u05dd",
        "FileName": "22044620.X01",
        "DocName": "22044620.X01.docx",
        "Content": null,
        "Year": 2022,
        "TypeCode": 1,
        "Type": "\u05d4\u05d7\u05dc\u05d8\u05d4",
        "CaseDt": null,
        "MadorDesc": null,
        "SeqNum": 0,
        "Technical": true,
        "FolderPath": "HebrewVerdicts\\22\\620\\044\\x01",
        "PageVolume": null,
        "DescVolume": null,
        "CodeVolume": 0,
        "liked": false,
        "InyanId": 8,
        "QuoteYear": 0,
        "CodeQuote": null,
        "CodeTitle": null,
        "VerdictDesc": null,
        "DocNumber": null,
        "Month": null,
        "free_text": null
    }
]